CHANGES.txt
MANIFEST.in
README.md
setup.cfg
setup.py
por/__init__.py
por.dashboard.egg-info/PKG-INFO
por.dashboard.egg-info/SOURCES.txt
por.dashboard.egg-info/dependency_links.txt
por.dashboard.egg-info/entry_points.txt
por.dashboard.egg-info/namespace_packages.txt
por.dashboard.egg-info/not-zip-safe
por.dashboard.egg-info/requires.txt
por.dashboard.egg-info/top_level.txt
por/dashboard/__init__.py
por/dashboard/api.py
por/dashboard/backlog.py
por/dashboard/breadcrumbs.py
por/dashboard/build_18n_po.sh
por/dashboard/events.py
por/dashboard/fanstatic_resources.py
por/dashboard/html2text.py
por/dashboard/interfaces.py
por/dashboard/manage.py
por/dashboard/messages.py
por/dashboard/ravenlog.py
por/dashboard/renderers.py
por/dashboard/search.py
por/dashboard/sidebar.py
por/dashboard/smartadd.py
por/dashboard/tp.py
por/dashboard/views.py
por/dashboard/workflow.zcml
por/dashboard/deform_templates/chosen_multiple.pt
por/dashboard/deform_templates/dateinput.pt
por/dashboard/deform_templates/form.pt
por/dashboard/deform_templates/mapping_item.pt
por/dashboard/deform_templates/textinput.pt
por/dashboard/forms/__init__.py
por/dashboard/forms/application.py
por/dashboard/forms/application_views.py
por/dashboard/forms/contract.py
por/dashboard/forms/customer.py
por/dashboard/forms/customer_request.py
por/dashboard/forms/fast_ticketing.py
por/dashboard/forms/group.py
por/dashboard/forms/project.py
por/dashboard/forms/renderers.py
por/dashboard/forms/role.py
por/dashboard/forms/timeentry.py
por/dashboard/forms/user.py
por/dashboard/forms/wizard.py
por/dashboard/forms/workflow.py
por/dashboard/forms/templates/add_project.pt
por/dashboard/forms/templates/application_acl.pt
por/dashboard/forms/templates/application_generic_view.pt
por/dashboard/forms/templates/application_googledocument_view.pt
por/dashboard/forms/templates/application_googlefolder_view.pt
por/dashboard/forms/templates/application_show.pt
por/dashboard/forms/templates/application_trac_report.pt
por/dashboard/forms/templates/configurate_apps.pt
por/dashboard/forms/templates/configuration.pt
por/dashboard/forms/templates/contracts.pt
por/dashboard/forms/templates/customer.pt
por/dashboard/forms/templates/customer_listing.pt
por/dashboard/forms/templates/customer_projects.pt
